anfema_django_utils/__init__.py
anfema_django_utils/apps/__init__.py
anfema_django_utils/apps/admin_modelfilter/__init__.py
anfema_django_utils/apps/admin_modelfilter/apps.py
anfema_django_utils/apps/admin_modelfilter/tests.py
anfema_django_utils/apps/admin_modelfilter/static/admin/css/modelfilter.css
anfema_django_utils/apps/admin_modelfilter/static/admin/js/modelfilter.js
anfema_django_utils/apps/admin_modelfilter/templates/admin/base_site.html
anfema_django_utils/caching/__init__.py
anfema_django_utils/db/__init__.py
anfema_django_utils/db/functions.py
anfema_django_utils/db/mixins.py
anfema_django_utils/db/triggers.py
anfema_django_utils/tests/__init__.py
anfema_django_utils/tests/test_deny_field_update_triggers.py
anfema_django_utils-1.5.0.dist-info/LICENSE
anfema_django_utils-1.5.0.dist-info/WHEEL
anfema_django_utils-1.5.0.dist-info/METADATA
anfema_django_utils-1.5.0.dist-info/RECORD
